fastapi_manager/__init__.py
fastapi_manager/decorators.py
fastapi_manager/managers.py
fastapi_manager/meta.py
fastapi_manager/pagination.py
fastapi_orm_manager-0.0.15.dist-info/METADATA
fastapi_orm_manager-0.0.15.dist-info/WHEEL
fastapi_orm_manager-0.0.15.dist-info/licenses/LICENSE
fastapi_orm_manager-0.0.15.dist-info/RECORD
